pyrelukko/__init__.py
pyrelukko/decorators.py
pyrelukko/relukko_client.py
pyrelukko/relukko_dto.py
pyrelukko/testcontainers.py
pyrelukko/version.py
pyrelukko-0.11.0.dist-info/licenses/LICENSE
pyrelukko-0.11.0.dist-info/WHEEL
pyrelukko-0.11.0.dist-info/METADATA
pyrelukko-0.11.0.dist-info/RECORD
