Metadata-Version: 2.4
Name: pyrelukko
Version: 0.11.0
Summary: The client library for Relukko can be found in module
Author-email: Reto Zingg <g.d0b3rm4n@gmail.com>
Requires-Python: >=3.11
Classifier: Development Status :: 5 - Production/Stable
Classifier: Intended Audience :: Developers
Classifier: License :: OSI Approved :: MIT License
Classifier: Topic :: Internet :: WWW/HTTP
Classifier: Topic :: Software Development :: Libraries :: Python Modules
Classifier: Programming Language :: Python :: 3.11
Classifier: Programming Language :: Python :: 3.12
Classifier: Programming Language :: Python :: 3.13
Classifier: Programming Language :: Python :: 3.14
License-File: LICENSE
Requires-Dist: requests >=2.32.5
Requires-Dist: websockets >= 15.0
Project-URL: Homepage, https://gitlab.com/relukko/pyrelukko
Project-URL: Issues, https://gitlab.com/relukko/pyrelukko/-/issues
